[{"line":2,"elements":[{"line":3,"name":"","description":"","type":"background","keyword":"Background","steps":[{"result":{"duration":1037600254,"status":"passed"},"line":4,"name":"user is on login page","match":{"location":"org.davinatw.WebUITest.stepdef.LoginStepDef.userIsOnLoginPage()"},"keyword":"Given "},{"result":{"duration":243696730,"status":"passed"},"line":5,"name":"user input username with \"standard_user\"","match":{"arguments":[{"val":"\"standard_user\"","offset":25}],"location":"org.davinatw.WebUITest.stepdef.LoginStepDef.userInputUsernameWith(java.lang.String)"},"keyword":"And "},{"result":{"duration":68381455,"status":"passed"},"line":6,"name":"user input password with \"secret_sauce\"","match":{"arguments":[{"val":"\"secret_sauce\"","offset":25}],"location":"org.davinatw.WebUITest.stepdef.LoginStepDef.userInputPasswordWith(java.lang.String)"},"keyword":"And "},{"result":{"duration":230632960,"status":"passed"},"line":7,"name":"user click login button","match":{"location":"org.davinatw.WebUITest.stepdef.LoginStepDef.userClickLoginButton()"},"keyword":"And "}]},{"start_timestamp":"2026-01-18T15:14:15.172Z","before":[{"result":{"duration":8277161168,"status":"passed"},"match":{"location":"org.davinatw.WebUITest.stepdef.CucumberHooks.beforeTest()"}}],"line":10,"name":"Successfully add an item to the cart","description":"","id":"cart;successfully-add-an-item-to-the-cart","after":[{"result":{"duration":104922557,"status":"passed"},"match":{"location":"org.davinatw.WebUITest.stepdef.CucumberHooks.afterTest()"}}],"type":"scenario","keyword":"Scenario","steps":[{"result":{"duration":28381562,"status":"passed"},"line":11,"name":"user is on home page","match":{"location":"org.davinatw.WebUITest.stepdef.HomeStepDef.userIsOnHomepage()"},"keyword":"Given "},{"result":{"duration":67269683,"status":"passed"},"line":12,"name":"user clicks add to cart button on the first item","match":{"location":"org.davinatw.WebUITest.stepdef.HomeStepDef.userClickAddToCartButton()"},"keyword":"When "},{"result":{"duration":20346006,"status":"passed"},"line":13,"name":"add to cart button changes to remove button","match":{"location":"org.davinatw.WebUITest.stepdef.HomeStepDef.addToCartButtonChangesToRemove()"},"keyword":"Then "},{"result":{"duration":21064121,"status":"passed"},"line":14,"name":"cart icon shows item count","match":{"location":"org.davinatw.WebUITest.stepdef.HomeStepDef.cartIconShowsItemCount()"},"keyword":"And "}],"tags":[{"name":"@web"},{"name":"@test-positive"}]},{"line":3,"name":"","description":"","type":"background","keyword":"Background","steps":[{"result":{"duration":306298762,"status":"passed"},"line":4,"name":"user is on login page","match":{"location":"org.davinatw.WebUITest.stepdef.LoginStepDef.userIsOnLoginPage()"},"keyword":"Given "},{"result":{"duration":80407687,"status":"passed"},"line":5,"name":"user input username with \"standard_user\"","match":{"arguments":[{"val":"\"standard_user\"","offset":25}],"location":"org.davinatw.WebUITest.stepdef.LoginStepDef.userInputUsernameWith(java.lang.String)"},"keyword":"And "},{"result":{"duration":68104334,"status":"passed"},"line":6,"name":"user input password with \"secret_sauce\"","match":{"arguments":[{"val":"\"secret_sauce\"","offset":25}],"location":"org.davinatw.WebUITest.stepdef.LoginStepDef.userInputPasswordWith(java.lang.String)"},"keyword":"And "},{"result":{"duration":88386696,"status":"passed"},"line":7,"name":"user click login button","match":{"location":"org.davinatw.WebUITest.stepdef.LoginStepDef.userClickLoginButton()"},"keyword":"And "}]},{"start_timestamp":"2026-01-18T15:14:25.306Z","before":[{"result":{"duration":312513513,"status":"passed"},"match":{"location":"org.davinatw.WebUITest.stepdef.CucumberHooks.beforeTest()"}}],"line":17,"name":"Successfully remove an item from the cart","description":"","id":"cart;successfully-remove-an-item-from-the-cart","after":[{"result":{"duration":104104610,"status":"passed"},"match":{"location":"org.davinatw.WebUITest.stepdef.CucumberHooks.afterTest()"}}],"type":"scenario","keyword":"Scenario","steps":[{"result":{"duration":36053530,"status":"passed"},"line":18,"name":"user is on home page","match":{"location":"org.davinatw.WebUITest.stepdef.HomeStepDef.userIsOnHomepage()"},"keyword":"Given "},{"result":{"duration":59971454,"status":"passed"},"line":19,"name":"user clicks cart icon button on the first item","match":{"location":"org.davinatw.WebUITest.stepdef.CartStepDef.clickCartIconButtonOnTheFirstItem()"},"keyword":"And "},{"result":{"duration":90659172,"status":"passed"},"line":20,"name":"user clicks cart icon button","match":{"location":"org.davinatw.WebUITest.stepdef.CartStepDef.clickCartIconButton()"},"keyword":"And "},{"result":{"duration":9798241,"status":"passed"},"line":21,"name":"user is on cart page","match":{"location":"org.davinatw.WebUITest.stepdef.CartStepDef.isOnCartPage()"},"keyword":"And "},{"result":{"duration":112598301,"status":"passed"},"line":22,"name":"user clicks remove button","match":{"location":"org.davinatw.WebUITest.stepdef.CartStepDef.clickRemoveButton()"},"keyword":"When "},{"result":{"error_message":"org.openqa.selenium.TimeoutException: Expected condition failed: waiting for element to no longer be visible: By.xpath: //div[@class='inventory_item_name' and text()='Sauce Labs Backpack'] (tried for 10 second(s) with 500 milliseconds interval)\nBuild info: version: '4.29.0', revision: '5fc1ec94cb'\nSystem info: os.name: 'Linux', os.arch: 'amd64', os.version: '6.11.0-1018-azure', java.version: '17.0.17'\nDriver info: org.openqa.selenium.chrome.ChromeDriver\nCapabilities {acceptInsecureCerts: false, browserName: chrome, browserVersion: 143.0.7499.192, chrome: {chromedriverVersion: 143.0.7499.192 (be2c1f4fd45..., userDataDir: /tmp/.org.chromium.Chromium...}, fedcm:accounts: true, goog:chromeOptions: {debuggerAddress: localhost:38931}, goog:processID: 2483, networkConnectionEnabled: false, pageLoadStrategy: normal, platformName: linux, proxy: Proxy(), se:cdp: ws://localhost:38931/devtoo..., se:cdpVersion: 143.0.7499.192, setWindowRect: true, strictFileInteractability: false, timeouts: {implicit: 0, pageLoad: 300000, script: 30000}, unhandledPromptBehavior: dismiss and notify, webauthn:extension:credBlob: true, webauthn:extension:largeBlob: true, webauthn:extension:minPinLength: true, webauthn:extension:prf: true, webauthn:virtualAuthenticators: true}\nSession ID: 4e4b1abb2a59c29417f85ce8f110f83c\n\tat org.openqa.selenium.support.ui.WebDriverWait.timeoutException(WebDriverWait.java:84)\n\tat org.openqa.selenium.support.ui.FluentWait.until(FluentWait.java:228)\n\tat org.davinatw.WebUITest.page.CartPage.isCartEmpty(CartPage.java:80)\n\tat org.davinatw.WebUITest.stepdef.CartStepDef.validateItemNotExist(CartStepDef.java:42)\n\tat ✽.the cart item \"Sauce Labs Backpack\" should not be visible(file:///home/runner/work/Jayjay-Modul24-FinalProject/Jayjay-Modul24-FinalProject/src/test/resources/Web/cart.feature:23)\n","duration":10302513842,"status":"failed"},"line":23,"name":"the cart item \"Sauce Labs Backpack\" should not be visible","match":{"arguments":[{"val":"\"Sauce Labs Backpack\"","offset":14}],"location":"org.davinatw.WebUITest.stepdef.CartStepDef.validateItemNotExist(java.lang.String)"},"keyword":"Then "}],"tags":[{"name":"@web"},{"name":"@test-positive"}]}],"name":"Cart","description":"","id":"cart","keyword":"Feature","uri":"file:src/test/resources/Web/cart.feature","tags":[{"name":"@web","type":"Tag","location":{"line":1,"column":1}}]},{"line":2,"elements":[{"line":3,"name":"","description":"","type":"background","keyword":"Background","steps":[{"result":{"duration":515653130,"status":"passed"},"line":4,"name":"the user is logged in","match":{"location":"org.davinatw.WebUITest.stepdef.LoginStepDef.theUserIsLoggedIn()"},"keyword":"Given "},{"result":{"duration":69973126,"status":"passed"},"line":5,"name":"user clicks cart icon button on the first item","match":{"location":"org.davinatw.WebUITest.stepdef.CartStepDef.clickCartIconButtonOnTheFirstItem()"},"keyword":"And "}]},{"start_timestamp":"2026-01-18T15:14:36.893Z","before":[{"result":{"duration":227871915,"status":"passed"},"match":{"location":"org.davinatw.WebUITest.stepdef.CucumberHooks.beforeTest()"}}],"line":9,"name":"Successfully checkout with valid inputs","description":"","id":"checkout;successfully-checkout-with-valid-inputs","after":[{"result":{"duration":103544656,"status":"passed"},"match":{"location":"org.davinatw.WebUITest.stepdef.CucumberHooks.afterTest()"}}],"type":"scenario","keyword":"Scenario","steps":[{"result":{"duration":19549335,"status":"passed"},"line":10,"name":"user is on home page","match":{"location":"org.davinatw.WebUITest.stepdef.HomeStepDef.userIsOnHomepage()"},"keyword":"Given "},{"result":{"duration":78515874,"status":"passed"},"line":11,"name":"user clicks cart icon button","match":{"location":"org.davinatw.WebUITest.stepdef.CartStepDef.clickCartIconButton()"},"keyword":"And "},{"result":{"duration":6774708,"status":"passed"},"line":12,"name":"user is on cart page","match":{"location":"org.davinatw.WebUITest.stepdef.CartStepDef.isOnCartPage()"},"keyword":"And "},{"result":{"duration":10168953421,"status":"passed"},"line":13,"name":"user clicks the checkout button","match":{"location":"org.davinatw.WebUITest.stepdef.CheckoutStepDef.clickCheckoutButton()"},"keyword":"When "},{"result":{"duration":7638654,"status":"passed"},"line":14,"name":"user is on checkout first page","match":{"location":"org.davinatw.WebUITest.stepdef.CheckoutStepDef.isOnCheckoutFirstPage()"},"keyword":"And "},{"result":{"duration":59883507,"status":"passed"},"line":15,"name":"user input first name with \"Davina\"","match":{"arguments":[{"val":"\"Davina\"","offset":27}],"location":"org.davinatw.WebUITest.stepdef.CheckoutStepDef.inputFirstNameWith(java.lang.String)"},"keyword":"And "},{"result":{"duration":41818496,"status":"passed"},"line":16,"name":"user input last name with \"Wijaya\"","match":{"arguments":[{"val":"\"Wijaya\"","offset":26}],"location":"org.davinatw.WebUITest.stepdef.CheckoutStepDef.inputsLastNameWith(java.lang.String)"},"keyword":"And "},{"result":{"duration":40321607,"status":"passed"},"line":17,"name":"user input Zip code with \"123456\"","match":{"arguments":[{"val":"\"123456\"","offset":25}],"location":"org.davinatw.WebUITest.stepdef.CheckoutStepDef.inputZipCodeWith(java.lang.String)"},"keyword":"And "},{"result":{"duration":60317333,"status":"passed"},"line":18,"name":"user clicks the continue button","match":{"location":"org.davinatw.WebUITest.stepdef.CheckoutStepDef.clickContinueButton()"},"keyword":"And "},{"result":{"error_message":"java.lang.AssertionError\n\tat org.junit.Assert.fail(Assert.java:87)\n\tat org.junit.Assert.assertTrue(Assert.java:42)\n\tat org.junit.Assert.assertTrue(Assert.java:53)\n\tat org.davinatw.WebUITest.stepdef.CheckoutStepDef.isOnCheckoutSecondPage(CheckoutStepDef.java:58)\n\tat ✽.user is on checkout second page(file:///home/runner/work/Jayjay-Modul24-FinalProject/Jayjay-Modul24-FinalProject/src/test/resources/Web/checkout.feature:19)\n","duration":10099319925,"status":"failed"},"line":19,"name":"user is on checkout second page","match":{"location":"org.davinatw.WebUITest.stepdef.CheckoutStepDef.isOnCheckoutSecondPage()"},"keyword":"Then "},{"result":{"duration":67837,"status":"skipped"},"line":20,"name":"user sees the total price and the items to checkout","match":{"location":"org.davinatw.WebUITest.stepdef.CheckoutStepDef.seesTotalPriceAndItemsToCheckout()"},"keyword":"And "},{"result":{"duration":44624,"status":"skipped"},"line":21,"name":"user clicks the finish button","match":{"location":"org.davinatw.WebUITest.stepdef.CheckoutStepDef.clickFinishButton()"},"keyword":"When "},{"result":{"duration":53880,"status":"skipped"},"line":22,"name":"user sees the checkout complete message","match":{"location":"org.davinatw.WebUITest.stepdef.CheckoutStepDef.seesTheCheckoutCompleteMessage()"},"keyword":"Then "}],"tags":[{"name":"@web"},{"name":"@test-positive"}]},{"line":3,"name":"","description":"","type":"background","keyword":"Background","steps":[{"result":{"duration":507090529,"status":"passed"},"line":4,"name":"the user is logged in","match":{"location":"org.davinatw.WebUITest.stepdef.LoginStepDef.theUserIsLoggedIn()"},"keyword":"Given "},{"result":{"duration":73826176,"status":"passed"},"line":5,"name":"user clicks cart icon button on the first item","match":{"location":"org.davinatw.WebUITest.stepdef.CartStepDef.clickCartIconButtonOnTheFirstItem()"},"keyword":"And "}]},{"start_timestamp":"2026-01-18T15:14:58.407Z","before":[{"result":{"duration":229902629,"status":"passed"},"match":{"location":"org.davinatw.WebUITest.stepdef.CucumberHooks.beforeTest()"}}],"line":25,"name":"Validate user cancels checkout","description":"","id":"checkout;validate-user-cancels-checkout","after":[{"result":{"duration":103408123,"status":"passed"},"match":{"location":"org.davinatw.WebUITest.stepdef.CucumberHooks.afterTest()"}}],"type":"scenario","keyword":"Scenario","steps":[{"result":{"duration":20326596,"status":"passed"},"line":26,"name":"user is on home page","match":{"location":"org.davinatw.WebUITest.stepdef.HomeStepDef.userIsOnHomepage()"},"keyword":"Given "},{"result":{"duration":78192695,"status":"passed"},"line":27,"name":"user clicks cart icon button","match":{"location":"org.davinatw.WebUITest.stepdef.CartStepDef.clickCartIconButton()"},"keyword":"And "},{"result":{"duration":7938271,"status":"passed"},"line":28,"name":"user is on cart page","match":{"location":"org.davinatw.WebUITest.stepdef.CartStepDef.isOnCartPage()"},"keyword":"And "},{"result":{"duration":55687214,"status":"passed"},"line":29,"name":"user clicks the continue shopping button","match":{"location":"org.davinatw.WebUITest.stepdef.CheckoutStepDef.clickContinueShoppingButton()"},"keyword":"When "},{"result":{"duration":13098154,"status":"passed"},"line":30,"name":"user should be directed to home page","match":{"location":"org.davinatw.WebUITest.stepdef.HomeStepDef.validateUserIsOnHomepage()"},"keyword":"Then "}],"tags":[{"name":"@web"},{"name":"@test-negative"}]},{"line":3,"name":"","description":"","type":"background","keyword":"Background","steps":[{"result":{"duration":511648522,"status":"passed"},"line":4,"name":"the user is logged in","match":{"location":"org.davinatw.WebUITest.stepdef.LoginStepDef.theUserIsLoggedIn()"},"keyword":"Given "},{"result":{"duration":71053508,"status":"passed"},"line":5,"name":"user clicks cart icon button on the first item","match":{"location":"org.davinatw.WebUITest.stepdef.CartStepDef.clickCartIconButtonOnTheFirstItem()"},"keyword":"And "}]},{"start_timestamp":"2026-01-18T15:14:59.505Z","before":[{"result":{"duration":233767672,"status":"passed"},"match":{"location":"org.davinatw.WebUITest.stepdef.CucumberHooks.beforeTest()"}}],"line":47,"name":"Validate user cannot checkout with empty fields","description":"","id":"checkout;validate-user-cannot-checkout-with-empty-fields;;2","after":[{"result":{"duration":103278407,"status":"passed"},"match":{"location":"org.davinatw.WebUITest.stepdef.CucumberHooks.afterTest()"}}],"type":"scenario","keyword":"Scenario Outline","steps":[{"result":{"duration":18365198,"status":"passed"},"line":34,"name":"user is on home page","match":{"location":"org.davinatw.WebUITest.stepdef.HomeStepDef.userIsOnHomepage()"},"keyword":"Given "},{"result":{"duration":77819488,"status":"passed"},"line":35,"name":"user clicks cart icon button","match":{"location":"org.davinatw.WebUITest.stepdef.CartStepDef.clickCartIconButton()"},"keyword":"And "},{"result":{"duration":6632490,"status":"passed"},"line":36,"name":"user is on cart page","match":{"location":"org.davinatw.WebUITest.stepdef.CartStepDef.isOnCartPage()"},"keyword":"And "},{"result":{"duration":10166198866,"status":"passed"},"line":37,"name":"user clicks the checkout button","match":{"location":"org.davinatw.WebUITest.stepdef.CheckoutStepDef.clickCheckoutButton()"},"keyword":"When "},{"result":{"duration":6830046,"status":"passed"},"line":38,"name":"user is on checkout first page","match":{"location":"org.davinatw.WebUITest.stepdef.CheckoutStepDef.isOnCheckoutFirstPage()"},"keyword":"And "},{"result":{"duration":46973926,"status":"passed"},"line":39,"name":"user input first name with \"\"","match":{"arguments":[{"val":"\"\"","offset":27}],"location":"org.davinatw.WebUITest.stepdef.CheckoutStepDef.inputFirstNameWith(java.lang.String)"},"keyword":"And "},{"result":{"duration":39516081,"status":"passed"},"line":40,"name":"user input last name with \"\"","match":{"arguments":[{"val":"\"\"","offset":26}],"location":"org.davinatw.WebUITest.stepdef.CheckoutStepDef.inputsLastNameWith(java.lang.String)"},"keyword":"And "},{"result":{"duration":40430832,"status":"passed"},"line":41,"name":"user input Zip code with \"\"","match":{"arguments":[{"val":"\"\"","offset":25}],"location":"org.davinatw.WebUITest.stepdef.CheckoutStepDef.inputZipCodeWith(java.lang.String)"},"keyword":"And "},{"result":{"duration":60248045,"status":"passed"},"line":42,"name":"user clicks the continue button","match":{"location":"org.davinatw.WebUITest.stepdef.CheckoutStepDef.clickContinueButton()"},"keyword":"And "},{"result":{"error_message":"org.junit.ComparisonFailure: expected:<[Error: First Name is required]> but was:<[]>\n\tat org.junit.Assert.assertEquals(Assert.java:117)\n\tat org.junit.Assert.assertEquals(Assert.java:146)\n\tat org.davinatw.WebUITest.stepdef.CheckoutStepDef.displaysTheErrorMessage(CheckoutStepDef.java:84)\n\tat ✽.the system displays the error message \"Error: First Name is required\"(file:///home/runner/work/Jayjay-Modul24-FinalProject/Jayjay-Modul24-FinalProject/src/test/resources/Web/checkout.feature:43)\n","duration":19434249,"status":"failed"},"line":43,"name":"the system displays the error message \"Error: First Name is required\"","match":{"arguments":[{"val":"\"Error: First Name is required\"","offset":38}],"location":"org.davinatw.WebUITest.stepdef.CheckoutStepDef.displaysTheErrorMessage(java.lang.String)"},"keyword":"Then "}],"tags":[{"name":"@web"},{"name":"@test-boundary"}]},{"line":3,"name":"","description":"","type":"background","keyword":"Background","steps":[{"result":{"duration":502930196,"status":"passed"},"line":4,"name":"the user is logged in","match":{"location":"org.davinatw.WebUITest.stepdef.LoginStepDef.theUserIsLoggedIn()"},"keyword":"Given "},{"result":{"duration":74152821,"status":"passed"},"line":5,"name":"user clicks cart icon button on the first item","match":{"location":"org.davinatw.WebUITest.stepdef.CartStepDef.clickCartIconButtonOnTheFirstItem()"},"keyword":"And "}]},{"start_timestamp":"2026-01-18T15:15:10.918Z","before":[{"result":{"duration":237445225,"status":"passed"},"match":{"location":"org.davinatw.WebUITest.stepdef.CucumberHooks.beforeTest()"}}],"line":48,"name":"Validate user cannot checkout with empty fields","description":"","id":"checkout;validate-user-cannot-checkout-with-empty-fields;;3","after":[{"result":{"duration":103182091,"status":"passed"},"match":{"location":"org.davinatw.WebUITest.stepdef.CucumberHooks.afterTest()"}}],"type":"scenario","keyword":"Scenario Outline","steps":[{"result":{"duration":20549027,"status":"passed"},"line":34,"name":"user is on home page","match":{"location":"org.davinatw.WebUITest.stepdef.HomeStepDef.userIsOnHomepage()"},"keyword":"Given "},{"result":{"duration":83967245,"status":"passed"},"line":35,"name":"user clicks cart icon button","match":{"location":"org.davinatw.WebUITest.stepdef.CartStepDef.clickCartIconButton()"},"keyword":"And "},{"result":{"duration":7224075,"status":"passed"},"line":36,"name":"user is on cart page","match":{"location":"org.davinatw.WebUITest.stepdef.CartStepDef.isOnCartPage()"},"keyword":"And "},{"result":{"duration":10163998073,"status":"passed"},"line":37,"name":"user clicks the checkout button","match":{"location":"org.davinatw.WebUITest.stepdef.CheckoutStepDef.clickCheckoutButton()"},"keyword":"When "},{"result":{"duration":6870000,"status":"passed"},"line":38,"name":"user is on checkout first page","match":{"location":"org.davinatw.WebUITest.stepdef.CheckoutStepDef.isOnCheckoutFirstPage()"},"keyword":"And "},{"result":{"duration":46550861,"status":"passed"},"line":39,"name":"user input first name with \"Davina\"","match":{"arguments":[{"val":"\"Davina\"","offset":27}],"location":"org.davinatw.WebUITest.stepdef.CheckoutStepDef.inputFirstNameWith(java.lang.String)"},"keyword":"And "},{"result":{"duration":40264281,"status":"passed"},"line":40,"name":"user input last name with \"\"","match":{"arguments":[{"val":"\"\"","offset":26}],"location":"org.davinatw.WebUITest.stepdef.CheckoutStepDef.inputsLastNameWith(java.lang.String)"},"keyword":"And "},{"result":{"duration":40344670,"status":"passed"},"line":41,"name":"user input Zip code with \"\"","match":{"arguments":[{"val":"\"\"","offset":25}],"location":"org.davinatw.WebUITest.stepdef.CheckoutStepDef.inputZipCodeWith(java.lang.String)"},"keyword":"And "},{"result":{"duration":63846538,"status":"passed"},"line":42,"name":"user clicks the continue button","match":{"location":"org.davinatw.WebUITest.stepdef.CheckoutStepDef.clickContinueButton()"},"keyword":"And "},{"result":{"error_message":"org.junit.ComparisonFailure: expected:<[Error: Last Name is required]> but was:<[]>\n\tat org.junit.Assert.assertEquals(Assert.java:117)\n\tat org.junit.Assert.assertEquals(Assert.java:146)\n\tat org.davinatw.WebUITest.stepdef.CheckoutStepDef.displaysTheErrorMessage(CheckoutStepDef.java:84)\n\tat ✽.the system displays the error message \"Error: Last Name is required\"(file:///home/runner/work/Jayjay-Modul24-FinalProject/Jayjay-Modul24-FinalProject/src/test/resources/Web/checkout.feature:43)\n","duration":19832584,"status":"failed"},"line":43,"name":"the system displays the error message \"Error: Last Name is required\"","match":{"arguments":[{"val":"\"Error: Last Name is required\"","offset":38}],"location":"org.davinatw.WebUITest.stepdef.CheckoutStepDef.displaysTheErrorMessage(java.lang.String)"},"keyword":"Then "}],"tags":[{"name":"@web"},{"name":"@test-boundary"}]},{"line":3,"name":"","description":"","type":"background","keyword":"Background","steps":[{"result":{"duration":500189962,"status":"passed"},"line":4,"name":"the user is logged in","match":{"location":"org.davinatw.WebUITest.stepdef.LoginStepDef.theUserIsLoggedIn()"},"keyword":"Given "},{"result":{"duration":70370521,"status":"passed"},"line":5,"name":"user clicks cart icon button on the first item","match":{"location":"org.davinatw.WebUITest.stepdef.CartStepDef.clickCartIconButtonOnTheFirstItem()"},"keyword":"And "}]},{"start_timestamp":"2026-01-18T15:15:22.344Z","before":[{"result":{"duration":218605800,"status":"passed"},"match":{"location":"org.davinatw.WebUITest.stepdef.CucumberHooks.beforeTest()"}}],"line":49,"name":"Validate user cannot checkout with empty fields","description":"","id":"checkout;validate-user-cannot-checkout-with-empty-fields;;4","after":[{"result":{"duration":103162153,"status":"passed"},"match":{"location":"org.davinatw.WebUITest.stepdef.CucumberHooks.afterTest()"}}],"type":"scenario","keyword":"Scenario Outline","steps":[{"result":{"duration":18878369,"status":"passed"},"line":34,"name":"user is on home page","match":{"location":"org.davinatw.WebUITest.stepdef.HomeStepDef.userIsOnHomepage()"},"keyword":"Given "},{"result":{"duration":76749277,"status":"passed"},"line":35,"name":"user clicks cart icon button","match":{"location":"org.davinatw.WebUITest.stepdef.CartStepDef.clickCartIconButton()"},"keyword":"And "},{"result":{"duration":7095234,"status":"passed"},"line":36,"name":"user is on cart page","match":{"location":"org.davinatw.WebUITest.stepdef.CartStepDef.isOnCartPage()"},"keyword":"And "},{"result":{"duration":69802242,"status":"passed"},"line":37,"name":"user clicks the checkout button","match":{"location":"org.davinatw.WebUITest.stepdef.CheckoutStepDef.clickCheckoutButton()"},"keyword":"When "},{"result":{"duration":8200913,"status":"passed"},"line":38,"name":"user is on checkout first page","match":{"location":"org.davinatw.WebUITest.stepdef.CheckoutStepDef.isOnCheckoutFirstPage()"},"keyword":"And "},{"result":{"duration":44837205,"status":"passed"},"line":39,"name":"user input first name with \"Davina\"","match":{"arguments":[{"val":"\"Davina\"","offset":27}],"location":"org.davinatw.WebUITest.stepdef.CheckoutStepDef.inputFirstNameWith(java.lang.String)"},"keyword":"And "},{"result":{"duration":40554442,"status":"passed"},"line":40,"name":"user input last name with \"Wijaya\"","match":{"arguments":[{"val":"\"Wijaya\"","offset":26}],"location":"org.davinatw.WebUITest.stepdef.CheckoutStepDef.inputsLastNameWith(java.lang.String)"},"keyword":"And "},{"result":{"duration":38684462,"status":"passed"},"line":41,"name":"user input Zip code with \"\"","match":{"arguments":[{"val":"\"\"","offset":25}],"location":"org.davinatw.WebUITest.stepdef.CheckoutStepDef.inputZipCodeWith(java.lang.String)"},"keyword":"And "},{"result":{"duration":59528630,"status":"passed"},"line":42,"name":"user clicks the continue button","match":{"location":"org.davinatw.WebUITest.stepdef.CheckoutStepDef.clickContinueButton()"},"keyword":"And "},{"result":{"error_message":"org.junit.ComparisonFailure: expected:<[Error: Postal Code is required]> but was:<[]>\n\tat org.junit.Assert.assertEquals(Assert.java:117)\n\tat org.junit.Assert.assertEquals(Assert.java:146)\n\tat org.davinatw.WebUITest.stepdef.CheckoutStepDef.displaysTheErrorMessage(CheckoutStepDef.java:84)\n\tat ✽.the system displays the error message \"Error: Postal Code is required\"(file:///home/runner/work/Jayjay-Modul24-FinalProject/Jayjay-Modul24-FinalProject/src/test/resources/Web/checkout.feature:43)\n","duration":19070889,"status":"failed"},"line":43,"name":"the system displays the error message \"Error: Postal Code is required\"","match":{"arguments":[{"val":"\"Error: Postal Code is required\"","offset":38}],"location":"org.davinatw.WebUITest.stepdef.CheckoutStepDef.displaysTheErrorMessage(java.lang.String)"},"keyword":"Then "}],"tags":[{"name":"@web"},{"name":"@test-boundary"}]}],"name":"Checkout","description":"","id":"checkout","keyword":"Feature","uri":"file:src/test/resources/Web/checkout.feature","tags":[{"name":"@web","type":"Tag","location":{"line":1,"column":1}}]},{"line":2,"elements":[{"line":3,"name":"","description":"","type":"background","keyword":"Background","steps":[{"result":{"duration":273037367,"status":"passed"},"line":4,"name":"user is on login page","match":{"location":"org.davinatw.WebUITest.stepdef.LoginStepDef.userIsOnLoginPage()"},"keyword":"Given "},{"result":{"duration":79888980,"status":"passed"},"line":5,"name":"user input username with \"standard_user\"","match":{"arguments":[{"val":"\"standard_user\"","offset":25}],"location":"org.davinatw.WebUITest.stepdef.LoginStepDef.userInputUsernameWith(java.lang.String)"},"keyword":"And "},{"result":{"duration":65126836,"status":"passed"},"line":6,"name":"user input password with \"secret_sauce\"","match":{"arguments":[{"val":"\"secret_sauce\"","offset":25}],"location":"org.davinatw.WebUITest.stepdef.LoginStepDef.userInputPasswordWith(java.lang.String)"},"keyword":"And "},{"result":{"duration":86613039,"status":"passed"},"line":7,"name":"user click login button","match":{"location":"org.davinatw.WebUITest.stepdef.LoginStepDef.userClickLoginButton()"},"keyword":"And "}]},{"start_timestamp":"2026-01-18T15:15:23.628Z","before":[{"result":{"duration":229896308,"status":"passed"},"match":{"location":"org.davinatw.WebUITest.stepdef.CucumberHooks.beforeTest()"}}],"line":10,"name":"Show products sorted by name (A to Z)","description":"","id":"filter;show-products-sorted-by-name-(a-to-z)","after":[{"result":{"duration":102950664,"status":"passed"},"match":{"location":"org.davinatw.WebUITest.stepdef.CucumberHooks.afterTest()"}}],"type":"scenario","keyword":"Scenario","steps":[{"result":{"duration":36699512,"status":"passed"},"line":11,"name":"user is on home page","match":{"location":"org.davinatw.WebUITest.stepdef.HomeStepDef.userIsOnHomepage()"},"keyword":"Given "},{"result":{"duration":50910734,"status":"passed"},"line":12,"name":"user clicks \"Name (A to Z)\"","match":{"arguments":[{"val":"\"Name (A to Z)\"","offset":12}],"location":"org.davinatw.WebUITest.stepdef.HomeStepDef.clickSort(java.lang.String)"},"keyword":"When "},{"result":{"duration":24654027,"status":"passed"},"line":13,"name":"user can see the first product named \"Sauce Labs Backpack\"","match":{"arguments":[{"val":"\"Sauce Labs Backpack\"","offset":37}],"location":"org.davinatw.WebUITest.stepdef.HomeStepDef.validateFirstProductName(java.lang.String)"},"keyword":"Then "},{"result":{"duration":13178215,"status":"passed"},"line":14,"name":"user can see the last product named \"Test.allTheThings() T-Shirt (Red)\"","match":{"arguments":[{"val":"\"Test.allTheThings() T-Shirt (Red)\"","offset":36}],"location":"org.davinatw.WebUITest.stepdef.HomeStepDef.validateLastProductName(java.lang.String)"},"keyword":"And "}],"tags":[{"name":"@web"},{"name":"@test-positive"}]},{"line":3,"name":"","description":"","type":"background","keyword":"Background","steps":[{"result":{"duration":275831514,"status":"passed"},"line":4,"name":"user is on login page","match":{"location":"org.davinatw.WebUITest.stepdef.LoginStepDef.userIsOnLoginPage()"},"keyword":"Given "},{"result":{"duration":83553278,"status":"passed"},"line":5,"name":"user input username with \"standard_user\"","match":{"arguments":[{"val":"\"standard_user\"","offset":25}],"location":"org.davinatw.WebUITest.stepdef.LoginStepDef.userInputUsernameWith(java.lang.String)"},"keyword":"And "},{"result":{"duration":62946264,"status":"passed"},"line":6,"name":"user input password with \"secret_sauce\"","match":{"arguments":[{"val":"\"secret_sauce\"","offset":25}],"location":"org.davinatw.WebUITest.stepdef.LoginStepDef.userInputPasswordWith(java.lang.String)"},"keyword":"And "},{"result":{"duration":87027917,"status":"passed"},"line":7,"name":"user click login button","match":{"location":"org.davinatw.WebUITest.stepdef.LoginStepDef.userClickLoginButton()"},"keyword":"And "}]},{"start_timestamp":"2026-01-18T15:15:24.600Z","before":[{"result":{"duration":217672577,"status":"passed"},"match":{"location":"org.davinatw.WebUITest.stepdef.CucumberHooks.beforeTest()"}}],"line":17,"name":"Show products sorted by name (Z to A)","description":"","id":"filter;show-products-sorted-by-name-(z-to-a)","after":[{"result":{"duration":104052070,"status":"passed"},"match":{"location":"org.davinatw.WebUITest.stepdef.CucumberHooks.afterTest()"}}],"type":"scenario","keyword":"Scenario","steps":[{"result":{"duration":32435703,"status":"passed"},"line":18,"name":"user is on home page","match":{"location":"org.davinatw.WebUITest.stepdef.HomeStepDef.userIsOnHomepage()"},"keyword":"Given "},{"result":{"duration":74698779,"status":"passed"},"line":19,"name":"user clicks \"Name (Z to A)\"","match":{"arguments":[{"val":"\"Name (Z to A)\"","offset":12}],"location":"org.davinatw.WebUITest.stepdef.HomeStepDef.clickSort(java.lang.String)"},"keyword":"When "},{"result":{"duration":23351700,"status":"passed"},"line":20,"name":"user can see the first product named \"Test.allTheThings() T-Shirt (Red)\"","match":{"arguments":[{"val":"\"Test.allTheThings() T-Shirt (Red)\"","offset":37}],"location":"org.davinatw.WebUITest.stepdef.HomeStepDef.validateFirstProductName(java.lang.String)"},"keyword":"Then "},{"result":{"duration":16250650,"status":"passed"},"line":21,"name":"user can see the last product named \"Sauce Labs Backpack\"","match":{"arguments":[{"val":"\"Sauce Labs Backpack\"","offset":36}],"location":"org.davinatw.WebUITest.stepdef.HomeStepDef.validateLastProductName(java.lang.String)"},"keyword":"And "}],"tags":[{"name":"@web"},{"name":"@test-positive"}]},{"line":3,"name":"","description":"","type":"background","keyword":"Background","steps":[{"result":{"duration":278676832,"status":"passed"},"line":4,"name":"user is on login page","match":{"location":"org.davinatw.WebUITest.stepdef.LoginStepDef.userIsOnLoginPage()"},"keyword":"Given "},{"result":{"duration":97524603,"status":"passed"},"line":5,"name":"user input username with \"standard_user\"","match":{"arguments":[{"val":"\"standard_user\"","offset":25}],"location":"org.davinatw.WebUITest.stepdef.LoginStepDef.userInputUsernameWith(java.lang.String)"},"keyword":"And "},{"result":{"duration":73281793,"status":"passed"},"line":6,"name":"user input password with \"secret_sauce\"","match":{"arguments":[{"val":"\"secret_sauce\"","offset":25}],"location":"org.davinatw.WebUITest.stepdef.LoginStepDef.userInputPasswordWith(java.lang.String)"},"keyword":"And "},{"result":{"duration":89496214,"status":"passed"},"line":7,"name":"user click login button","match":{"location":"org.davinatw.WebUITest.stepdef.LoginStepDef.userClickLoginButton()"},"keyword":"And "}]},{"start_timestamp":"2026-01-18T15:15:25.585Z","before":[{"result":{"duration":225294015,"status":"passed"},"match":{"location":"org.davinatw.WebUITest.stepdef.CucumberHooks.beforeTest()"}}],"line":24,"name":"Show products sorted by price (low to high)","description":"","id":"filter;show-products-sorted-by-price-(low-to-high)","after":[{"result":{"duration":102742865,"status":"passed"},"match":{"location":"org.davinatw.WebUITest.stepdef.CucumberHooks.afterTest()"}}],"type":"scenario","keyword":"Scenario","steps":[{"result":{"duration":34902692,"status":"passed"},"line":25,"name":"user is on home page","match":{"location":"org.davinatw.WebUITest.stepdef.HomeStepDef.userIsOnHomepage()"},"keyword":"Given "},{"result":{"duration":75526894,"status":"passed"},"line":26,"name":"user clicks \"Price (low to high)\"","match":{"arguments":[{"val":"\"Price (low to high)\"","offset":12}],"location":"org.davinatw.WebUITest.stepdef.HomeStepDef.clickSort(java.lang.String)"},"keyword":"When "},{"result":{"duration":21539512,"status":"passed"},"line":27,"name":"user can see the first product with price \"$7.99\"","match":{"arguments":[{"val":"\"$7.99\"","offset":42}],"location":"org.davinatw.WebUITest.stepdef.HomeStepDef.validateFirstProductPrice(java.lang.String)"},"keyword":"Then "},{"result":{"duration":14780910,"status":"passed"},"line":28,"name":"user can see the last product with price \"$49.99\"","match":{"arguments":[{"val":"\"$49.99\"","offset":41}],"location":"org.davinatw.WebUITest.stepdef.HomeStepDef.validateLastProductPrice(java.lang.String)"},"keyword":"And "}],"tags":[{"name":"@web"},{"name":"@test-positive"}]},{"line":3,"name":"","description":"","type":"background","keyword":"Background","steps":[{"result":{"duration":297119132,"status":"passed"},"line":4,"name":"user is on login page","match":{"location":"org.davinatw.WebUITest.stepdef.LoginStepDef.userIsOnLoginPage()"},"keyword":"Given "},{"result":{"duration":80439773,"status":"passed"},"line":5,"name":"user input username with \"standard_user\"","match":{"arguments":[{"val":"\"standard_user\"","offset":25}],"location":"org.davinatw.WebUITest.stepdef.LoginStepDef.userInputUsernameWith(java.lang.String)"},"keyword":"And "},{"result":{"duration":63475219,"status":"passed"},"line":6,"name":"user input password with \"secret_sauce\"","match":{"arguments":[{"val":"\"secret_sauce\"","offset":25}],"location":"org.davinatw.WebUITest.stepdef.LoginStepDef.userInputPasswordWith(java.lang.String)"},"keyword":"And "},{"result":{"duration":88230607,"status":"passed"},"line":7,"name":"user click login button","match":{"location":"org.davinatw.WebUITest.stepdef.LoginStepDef.userClickLoginButton()"},"keyword":"And "}]},{"start_timestamp":"2026-01-18T15:15:26.606Z","before":[{"result":{"duration":223603310,"status":"passed"},"match":{"location":"org.davinatw.WebUITest.stepdef.CucumberHooks.beforeTest()"}}],"line":31,"name":"Show products sorted by price (high to low)","description":"","id":"filter;show-products-sorted-by-price-(high-to-low)","after":[{"result":{"duration":103148684,"status":"passed"},"match":{"location":"org.davinatw.WebUITest.stepdef.CucumberHooks.afterTest()"}}],"type":"scenario","keyword":"Scenario","steps":[{"result":{"duration":33537428,"status":"passed"},"line":32,"name":"user is on home page","match":{"location":"org.davinatw.WebUITest.stepdef.HomeStepDef.userIsOnHomepage()"},"keyword":"Given "},{"result":{"duration":84302417,"status":"passed"},"line":33,"name":"user clicks \"Price (high to low)\"","match":{"arguments":[{"val":"\"Price (high to low)\"","offset":12}],"location":"org.davinatw.WebUITest.stepdef.HomeStepDef.clickSort(java.lang.String)"},"keyword":"When "},{"result":{"duration":24626487,"status":"passed"},"line":34,"name":"user can see the first product with price \"$49.99\"","match":{"arguments":[{"val":"\"$49.99\"","offset":42}],"location":"org.davinatw.WebUITest.stepdef.HomeStepDef.validateFirstProductPrice(java.lang.String)"},"keyword":"Then "},{"result":{"duration":15514895,"status":"passed"},"line":35,"name":"user can see the last product with price \"$7.99\"","match":{"arguments":[{"val":"\"$7.99\"","offset":41}],"location":"org.davinatw.WebUITest.stepdef.HomeStepDef.validateLastProductPrice(java.lang.String)"},"keyword":"And "}],"tags":[{"name":"@web"},{"name":"@test-positive"}]}],"name":"Filter","description":"","id":"filter","keyword":"Feature","uri":"file:src/test/resources/Web/filter.feature","tags":[{"name":"@web","type":"Tag","location":{"line":1,"column":1}}]},{"line":2,"elements":[{"start_timestamp":"2026-01-18T15:15:27.627Z","before":[{"result":{"duration":216585653,"status":"passed"},"match":{"location":"org.davinatw.WebUITest.stepdef.CucumberHooks.beforeTest()"}}],"line":5,"name":"Login using invalid username and password","description":"","id":"login;login-using-invalid-username-and-password","after":[{"result":{"duration":103223053,"status":"passed"},"match":{"location":"org.davinatw.WebUITest.stepdef.CucumberHooks.afterTest()"}}],"type":"scenario","keyword":"Scenario","steps":[{"result":{"duration":292168971,"status":"passed"},"line":6,"name":"user is on login page","match":{"location":"org.davinatw.WebUITest.stepdef.LoginStepDef.userIsOnLoginPage()"},"keyword":"Given "},{"result":{"duration":69165212,"status":"passed"},"line":7,"name":"user input username with \"std\"","match":{"arguments":[{"val":"\"std\"","offset":25}],"location":"org.davinatw.WebUITest.stepdef.LoginStepDef.userInputUsernameWith(java.lang.String)"},"keyword":"And "},{"result":{"duration":62085206,"status":"passed"},"line":8,"name":"user input password with \"secretsauce\"","match":{"arguments":[{"val":"\"secretsauce\"","offset":25}],"location":"org.davinatw.WebUITest.stepdef.LoginStepDef.userInputPasswordWith(java.lang.String)"},"keyword":"And "},{"result":{"duration":79225774,"status":"passed"},"line":9,"name":"user click login button","match":{"location":"org.davinatw.WebUITest.stepdef.LoginStepDef.userClickLoginButton()"},"keyword":"When "},{"result":{"duration":9891441,"status":"passed"},"line":10,"name":"user see error message \"Epic sadface: Username and password do not match any user in this service\"","match":{"arguments":[{"val":"\"Epic sadface: Username and password do not match any user in this service\"","offset":23}],"location":"org.davinatw.WebUITest.stepdef.LoginStepDef.userSeeErrorMessage(java.lang.String)"},"keyword":"Then "}],"tags":[{"name":"@web"},{"name":"@test-negative"}]},{"start_timestamp":"2026-01-18T15:15:28.467Z","before":[{"result":{"duration":235446426,"status":"passed"},"match":{"location":"org.davinatw.WebUITest.stepdef.CucumberHooks.beforeTest()"}}],"line":13,"name":"Login using user that has been locked out","description":"","id":"login;login-using-user-that-has-been-locked-out","after":[{"result":{"duration":103172498,"status":"passed"},"match":{"location":"org.davinatw.WebUITest.stepdef.CucumberHooks.afterTest()"}}],"type":"scenario","keyword":"Scenario","steps":[{"result":{"duration":282757747,"status":"passed"},"line":14,"name":"user is on login page","match":{"location":"org.davinatw.WebUITest.stepdef.LoginStepDef.userIsOnLoginPage()"},"keyword":"Given "},{"result":{"duration":83252563,"status":"passed"},"line":15,"name":"user input username with \"locked_out_user\"","match":{"arguments":[{"val":"\"locked_out_user\"","offset":25}],"location":"org.davinatw.WebUITest.stepdef.LoginStepDef.userInputUsernameWith(java.lang.String)"},"keyword":"And "},{"result":{"duration":68943250,"status":"passed"},"line":16,"name":"user input password with \"secret_sauce\"","match":{"arguments":[{"val":"\"secret_sauce\"","offset":25}],"location":"org.davinatw.WebUITest.stepdef.LoginStepDef.userInputPasswordWith(java.lang.String)"},"keyword":"And "},{"result":{"duration":73837532,"status":"passed"},"line":17,"name":"user click login button","match":{"location":"org.davinatw.WebUITest.stepdef.LoginStepDef.userClickLoginButton()"},"keyword":"When "},{"result":{"duration":6135637,"status":"passed"},"line":18,"name":"user see error message \"Epic sadface: Sorry, this user has been locked out.\"","match":{"arguments":[{"val":"\"Epic sadface: Sorry, this user has been locked out.\"","offset":23}],"location":"org.davinatw.WebUITest.stepdef.LoginStepDef.userSeeErrorMessage(java.lang.String)"},"keyword":"Then "}],"tags":[{"name":"@web"},{"name":"@test-negative"}]},{"start_timestamp":"2026-01-18T15:15:29.326Z","before":[{"result":{"duration":230686039,"status":"passed"},"match":{"location":"org.davinatw.WebUITest.stepdef.CucumberHooks.beforeTest()"}}],"line":21,"name":"Login using empty username and password","description":"","id":"login;login-using-empty-username-and-password","after":[{"result":{"duration":102778418,"status":"passed"},"match":{"location":"org.davinatw.WebUITest.stepdef.CucumberHooks.afterTest()"}}],"type":"scenario","keyword":"Scenario","steps":[{"result":{"duration":275877786,"status":"passed"},"line":22,"name":"user is on login page","match":{"location":"org.davinatw.WebUITest.stepdef.LoginStepDef.userIsOnLoginPage()"},"keyword":"Given "},{"result":{"duration":59883117,"status":"passed"},"line":23,"name":"user input username with \"\"","match":{"arguments":[{"val":"\"\"","offset":25}],"location":"org.davinatw.WebUITest.stepdef.LoginStepDef.userInputUsernameWith(java.lang.String)"},"keyword":"And "},{"result":{"duration":50972170,"status":"passed"},"line":24,"name":"user input password with \"\"","match":{"arguments":[{"val":"\"\"","offset":25}],"location":"org.davinatw.WebUITest.stepdef.LoginStepDef.userInputPasswordWith(java.lang.String)"},"keyword":"And "},{"result":{"duration":76632884,"status":"passed"},"line":25,"name":"user click login button","match":{"location":"org.davinatw.WebUITest.stepdef.LoginStepDef.userClickLoginButton()"},"keyword":"When "},{"result":{"duration":5306837,"status":"passed"},"line":26,"name":"user see error message \"Epic sadface: Username is required\"","match":{"arguments":[{"val":"\"Epic sadface: Username is required\"","offset":23}],"location":"org.davinatw.WebUITest.stepdef.LoginStepDef.userSeeErrorMessage(java.lang.String)"},"keyword":"Then "}],"tags":[{"name":"@web"},{"name":"@test-boundary"}]},{"start_timestamp":"2026-01-18T15:15:30.133Z","before":[{"result":{"duration":227746092,"status":"passed"},"match":{"location":"org.davinatw.WebUITest.stepdef.CucumberHooks.beforeTest()"}}],"line":37,"name":"Login using valid username and password","description":"","id":"login;login-using-valid-username-and-password;;2","after":[{"result":{"duration":103053487,"status":"passed"},"match":{"location":"org.davinatw.WebUITest.stepdef.CucumberHooks.afterTest()"}}],"type":"scenario","keyword":"Scenario Outline","steps":[{"result":{"duration":272232014,"status":"passed"},"line":30,"name":"user is on login page","match":{"location":"org.davinatw.WebUITest.stepdef.LoginStepDef.userIsOnLoginPage()"},"keyword":"Given "},{"result":{"duration":77318367,"status":"passed"},"line":31,"name":"user input username with \"standard_user\"","match":{"arguments":[{"val":"\"standard_user\"","offset":25}],"location":"org.davinatw.WebUITest.stepdef.LoginStepDef.userInputUsernameWith(java.lang.String)"},"keyword":"And "},{"result":{"duration":61765831,"status":"passed"},"line":32,"name":"user input password with \"secret_sauce\"","match":{"arguments":[{"val":"\"secret_sauce\"","offset":25}],"location":"org.davinatw.WebUITest.stepdef.LoginStepDef.userInputPasswordWith(java.lang.String)"},"keyword":"And "},{"result":{"duration":93345974,"status":"passed"},"line":33,"name":"user click login button","match":{"location":"org.davinatw.WebUITest.stepdef.LoginStepDef.userClickLoginButton()"},"keyword":"When "},{"result":{"duration":32079879,"status":"passed"},"line":34,"name":"user should be directed to home page","match":{"location":"org.davinatw.WebUITest.stepdef.HomeStepDef.validateUserIsOnHomepage()"},"keyword":"Then "}],"tags":[{"name":"@web"},{"name":"@test-positive"}]},{"start_timestamp":"2026-01-18T15:15:31.007Z","before":[{"result":{"duration":238476249,"status":"passed"},"match":{"location":"org.davinatw.WebUITest.stepdef.CucumberHooks.beforeTest()"}}],"line":38,"name":"Login using valid username and password","description":"","id":"login;login-using-valid-username-and-password;;3","after":[{"result":{"duration":103299177,"status":"passed"},"match":{"location":"org.davinatw.WebUITest.stepdef.CucumberHooks.afterTest()"}}],"type":"scenario","keyword":"Scenario Outline","steps":[{"result":{"duration":273147479,"status":"passed"},"line":30,"name":"user is on login page","match":{"location":"org.davinatw.WebUITest.stepdef.LoginStepDef.userIsOnLoginPage()"},"keyword":"Given "},{"result":{"duration":79859470,"status":"passed"},"line":31,"name":"user input username with \"problem_user\"","match":{"arguments":[{"val":"\"problem_user\"","offset":25}],"location":"org.davinatw.WebUITest.stepdef.LoginStepDef.userInputUsernameWith(java.lang.String)"},"keyword":"And "},{"result":{"duration":60791348,"status":"passed"},"line":32,"name":"user input password with \"secret_sauce\"","match":{"arguments":[{"val":"\"secret_sauce\"","offset":25}],"location":"org.davinatw.WebUITest.stepdef.LoginStepDef.userInputPasswordWith(java.lang.String)"},"keyword":"And "},{"result":{"duration":86955633,"status":"passed"},"line":33,"name":"user click login button","match":{"location":"org.davinatw.WebUITest.stepdef.LoginStepDef.userClickLoginButton()"},"keyword":"When "},{"result":{"duration":33878933,"status":"passed"},"line":34,"name":"user should be directed to home page","match":{"location":"org.davinatw.WebUITest.stepdef.HomeStepDef.validateUserIsOnHomepage()"},"keyword":"Then "}],"tags":[{"name":"@web"},{"name":"@test-positive"}]},{"start_timestamp":"2026-01-18T15:15:31.890Z","before":[{"result":{"duration":246743547,"status":"passed"},"match":{"location":"org.davinatw.WebUITest.stepdef.CucumberHooks.beforeTest()"}}],"line":39,"name":"Login using valid username and password","description":"","id":"login;login-using-valid-username-and-password;;4","after":[{"result":{"duration":102868829,"status":"passed"},"match":{"location":"org.davinatw.WebUITest.stepdef.CucumberHooks.afterTest()"}}],"type":"scenario","keyword":"Scenario Outline","steps":[{"result":{"duration":278010244,"status":"passed"},"line":30,"name":"user is on login page","match":{"location":"org.davinatw.WebUITest.stepdef.LoginStepDef.userIsOnLoginPage()"},"keyword":"Given "},{"result":{"duration":91464389,"status":"passed"},"line":31,"name":"user input username with \"performance_glitch_user\"","match":{"arguments":[{"val":"\"performance_glitch_user\"","offset":25}],"location":"org.davinatw.WebUITest.stepdef.LoginStepDef.userInputUsernameWith(java.lang.String)"},"keyword":"And "},{"result":{"duration":65619220,"status":"passed"},"line":32,"name":"user input password with \"secret_sauce\"","match":{"arguments":[{"val":"\"secret_sauce\"","offset":25}],"location":"org.davinatw.WebUITest.stepdef.LoginStepDef.userInputPasswordWith(java.lang.String)"},"keyword":"And "},{"result":{"duration":5092651644,"status":"passed"},"line":33,"name":"user click login button","match":{"location":"org.davinatw.WebUITest.stepdef.LoginStepDef.userClickLoginButton()"},"keyword":"When "},{"result":{"duration":21142086,"status":"passed"},"line":34,"name":"user should be directed to home page","match":{"location":"org.davinatw.WebUITest.stepdef.HomeStepDef.validateUserIsOnHomepage()"},"keyword":"Then "}],"tags":[{"name":"@web"},{"name":"@test-positive"}]},{"start_timestamp":"2026-01-18T15:15:37.793Z","before":[{"result":{"duration":226735252,"status":"passed"},"match":{"location":"org.davinatw.WebUITest.stepdef.CucumberHooks.beforeTest()"}}],"line":40,"name":"Login using valid username and password","description":"","id":"login;login-using-valid-username-and-password;;5","after":[{"result":{"duration":103259052,"status":"passed"},"match":{"location":"org.davinatw.WebUITest.stepdef.CucumberHooks.afterTest()"}}],"type":"scenario","keyword":"Scenario Outline","steps":[{"result":{"duration":275194512,"status":"passed"},"line":30,"name":"user is on login page","match":{"location":"org.davinatw.WebUITest.stepdef.LoginStepDef.userIsOnLoginPage()"},"keyword":"Given "},{"result":{"duration":77421066,"status":"passed"},"line":31,"name":"user input username with \"error_user\"","match":{"arguments":[{"val":"\"error_user\"","offset":25}],"location":"org.davinatw.WebUITest.stepdef.LoginStepDef.userInputUsernameWith(java.lang.String)"},"keyword":"And "},{"result":{"duration":68093034,"status":"passed"},"line":32,"name":"user input password with \"secret_sauce\"","match":{"arguments":[{"val":"\"secret_sauce\"","offset":25}],"location":"org.davinatw.WebUITest.stepdef.LoginStepDef.userInputPasswordWith(java.lang.String)"},"keyword":"And "},{"result":{"duration":88570429,"status":"passed"},"line":33,"name":"user click login button","match":{"location":"org.davinatw.WebUITest.stepdef.LoginStepDef.userClickLoginButton()"},"keyword":"When "},{"result":{"duration":31530801,"status":"passed"},"line":34,"name":"user should be directed to home page","match":{"location":"org.davinatw.WebUITest.stepdef.HomeStepDef.validateUserIsOnHomepage()"},"keyword":"Then "}],"tags":[{"name":"@web"},{"name":"@test-positive"}]},{"start_timestamp":"2026-01-18T15:15:38.669Z","before":[{"result":{"duration":222525706,"status":"passed"},"match":{"location":"org.davinatw.WebUITest.stepdef.CucumberHooks.beforeTest()"}}],"line":41,"name":"Login using valid username and password","description":"","id":"login;login-using-valid-username-and-password;;6","after":[{"result":{"duration":102879321,"status":"passed"},"match":{"location":"org.davinatw.WebUITest.stepdef.CucumberHooks.afterTest()"}}],"type":"scenario","keyword":"Scenario Outline","steps":[{"result":{"duration":284162596,"status":"passed"},"line":30,"name":"user is on login page","match":{"location":"org.davinatw.WebUITest.stepdef.LoginStepDef.userIsOnLoginPage()"},"keyword":"Given "},{"result":{"duration":79876570,"status":"passed"},"line":31,"name":"user input username with \"visual_user\"","match":{"arguments":[{"val":"\"visual_user\"","offset":25}],"location":"org.davinatw.WebUITest.stepdef.LoginStepDef.userInputUsernameWith(java.lang.String)"},"keyword":"And "},{"result":{"duration":65176657,"status":"passed"},"line":32,"name":"user input password with \"secret_sauce\"","match":{"arguments":[{"val":"\"secret_sauce\"","offset":25}],"location":"org.davinatw.WebUITest.stepdef.LoginStepDef.userInputPasswordWith(java.lang.String)"},"keyword":"And "},{"result":{"duration":86328341,"status":"passed"},"line":33,"name":"user click login button","match":{"location":"org.davinatw.WebUITest.stepdef.LoginStepDef.userClickLoginButton()"},"keyword":"When "},{"result":{"duration":34031520,"status":"passed"},"line":34,"name":"user should be directed to home page","match":{"location":"org.davinatw.WebUITest.stepdef.HomeStepDef.validateUserIsOnHomepage()"},"keyword":"Then "}],"tags":[{"name":"@web"},{"name":"@test-positive"}]}],"name":"Login","description":"","id":"login","keyword":"Feature","uri":"file:src/test/resources/Web/login.feature","tags":[{"name":"@web","type":"Tag","location":{"line":1,"column":1}}]},{"line":2,"elements":[{"line":3,"name":"","description":"","type":"background","keyword":"Background","steps":[{"result":{"duration":285482838,"status":"passed"},"line":4,"name":"user is on login page","match":{"location":"org.davinatw.WebUITest.stepdef.LoginStepDef.userIsOnLoginPage()"},"keyword":"Given "},{"result":{"duration":84056323,"status":"passed"},"line":5,"name":"user input username with \"standard_user\"","match":{"arguments":[{"val":"\"standard_user\"","offset":25}],"location":"org.davinatw.WebUITest.stepdef.LoginStepDef.userInputUsernameWith(java.lang.String)"},"keyword":"And "},{"result":{"duration":62201043,"status":"passed"},"line":6,"name":"user input password with \"secret_sauce\"","match":{"arguments":[{"val":"\"secret_sauce\"","offset":25}],"location":"org.davinatw.WebUITest.stepdef.LoginStepDef.userInputPasswordWith(java.lang.String)"},"keyword":"And "},{"result":{"duration":91874362,"status":"passed"},"line":7,"name":"user click login button","match":{"location":"org.davinatw.WebUITest.stepdef.LoginStepDef.userClickLoginButton()"},"keyword":"And "}]},{"start_timestamp":"2026-01-18T15:15:39.548Z","before":[{"result":{"duration":221857684,"status":"passed"},"match":{"location":"org.davinatw.WebUITest.stepdef.CucumberHooks.beforeTest()"}}],"line":10,"name":"logout from the website","description":"","id":"logout;logout-from-the-website","after":[{"result":{"duration":102823157,"status":"passed"},"match":{"location":"org.davinatw.WebUITest.stepdef.CucumberHooks.afterTest()"}}],"type":"scenario","keyword":"Scenario","steps":[{"result":{"duration":27852323,"status":"passed"},"line":11,"name":"user is on home page","match":{"location":"org.davinatw.WebUITest.stepdef.HomeStepDef.userIsOnHomepage()"},"keyword":"Given "},{"result":{"duration":54102964,"status":"passed"},"line":12,"name":"user click burger menu","match":{"location":"org.davinatw.WebUITest.stepdef.LogOutStepDef.clickBurgerMenu()"},"keyword":"When "},{"result":{"duration":543877914,"status":"passed"},"line":13,"name":"logout button displayed","match":{"location":"org.davinatw.WebUITest.stepdef.LogOutStepDef.logoutButtonDisplayed()"},"keyword":"And "},{"result":{"duration":22457386,"status":"passed"},"line":14,"name":"user click logout button","match":{"location":"org.davinatw.WebUITest.stepdef.LogOutStepDef.clickLogoutNavBar()"},"keyword":"And "},{"result":{"duration":7274981,"status":"passed"},"line":15,"name":"user should be directed to login page","match":{"location":"org.davinatw.WebUITest.stepdef.LogOutStepDef.validateToLoginPage()"},"keyword":"Then "}],"tags":[{"name":"@web"},{"name":"@test-positive"}]}],"name":"Logout","description":"","id":"logout","keyword":"Feature","uri":"file:src/test/resources/Web/logout.feature","tags":[{"name":"@web","type":"Tag","location":{"line":1,"column":1}}]}]